LICENSE.txt
MANIFEST.in
README.rst
setup.cfg
setup.py
yamlfred/__init__.py
yamlfred/alfred_connections.py
yamlfred/alfred_object.py
yamlfred/alfred_workflow.py
yamlfred/utils.py
yamlfred.egg-info/PKG-INFO
yamlfred.egg-info/SOURCES.txt
yamlfred.egg-info/dependency_links.txt
yamlfred.egg-info/entry_points.txt
yamlfred.egg-info/not-zip-safe
yamlfred.egg-info/pbr.json
yamlfred.egg-info/requires.txt
yamlfred.egg-info/top_level.txt