Metadata-Version: 1.1
Name: yamlfred
Version: 0.3.0
Summary: manage Alfred workflow via yaml templates
Home-page: https://github.com/uchida/yamlfred
Author: Akihiro Uchida
Author-email: uchida@turbare.net
License: CC0
Platform: UNKNOWN
Classifier: Development Status :: 1 - Planning
Classifier: Programming Language :: Python
